edu_convokit/__init__.py
edu_convokit/constants.py
edu_convokit/uptake_utils.py
edu_convokit/utils.py
edu_convokit/analyzers/__init__.py
edu_convokit/analyzers/analyzer.py
edu_convokit/analyzers/gpt_conversation_analyzer.py
edu_convokit/analyzers/lexical_analyzer.py
edu_convokit/analyzers/qualitative_analyzer.py
edu_convokit/analyzers/quantitative_analyzer.py
edu_convokit/analyzers/temporal_analyzer.py
edu_convokit/annotation/__init__.py
edu_convokit/annotation/annotator.py
edu_convokit/preprocessors/__init__.py
edu_convokit/preprocessors/text_preprocessor.py
edu_convokit/preprocessors/token_preprocessor.py
edu_convokit/prompts/conversation/class_clbm_bad_examples.txt
edu_convokit/prompts/conversation/class_clbm_good_examples.txt
edu_convokit/prompts/conversation/mqi_suggestions.txt
edu_convokit/prompts/conversation/summarize.txt
edu_convokit-0.4.0.dist-info/LICENSE
edu_convokit-0.4.0.dist-info/METADATA
edu_convokit-0.4.0.dist-info/WHEEL
edu_convokit-0.4.0.dist-info/top_level.txt
edu_convokit-0.4.0.dist-info/RECORD
