Metadata-Version: 2.1
Name: edu_convokit
Version: 0.4.0
Summary: Edu-ConvoKit: An Open-Source Framework for Education Conversation Data
Home-page: https://github.com/rosewang2008/edu-convokit
Author: Rose E. Wang
Author-email: rewang@cs.stanford.edu
License: MIT
Project-URL: Homepage, https://rosewang2008.github.io/edu-convokit/
Project-URL: Documentation, https://edu-convokit.readthedocs.io/en/latest/
Project-URL: Source, https://github.com/rosewang2008/edu-convokit/
Classifier: Programming Language :: Python :: 3
Classifier: Programming Language :: Python :: 3.7
Classifier: Programming Language :: Python :: 3.8
Classifier: Programming Language :: Python :: 3.9
Classifier: Programming Language :: Python :: 3.10
Classifier: License :: OSI Approved :: MIT License
Classifier: Operating System :: OS Independent
Classifier: Typing :: Typed
Classifier: Topic :: Scientific/Engineering :: Artificial Intelligence
Classifier: Topic :: Utilities
Requires-Python: >=3.10,<3.12
License-File: LICENSE
Requires-Dist: tqdm
Requires-Dist: numpy
Requires-Dist: scipy
Requires-Dist: nltk
Requires-Dist: torch
Requires-Dist: transformers
Requires-Dist: clean-text
Requires-Dist: openpyxl
Requires-Dist: spacy
Requires-Dist: gensim
Requires-Dist: num2words ==0.5.10
Requires-Dist: scikit-learn
Requires-Dist: matplotlib
Requires-Dist: seaborn
Requires-Dist: pandas
Requires-Dist: tiktoken
Requires-Dist: openai ==0.28
Requires-Dist: tenacity
Requires-Dist: python-dotenv
Provides-Extra: latex
Requires-Dist: bibtexparser ; extra == 'latex'
Provides-Extra: tests
Requires-Dist: pytest ; extra == 'tests'
